[
  {
    "Ticker": {
      "Symbol": "GOOGL"
    },
    "Bids": [
      {
        "Type": "Bid",
        "Price": 343434.0,
        "Quantity": 57153,
        "Total": 19628283402.0,
        "ProductType": "Futures",
        "Time": "2023-05-24T19:05:06.1066156+02:00"
      },
      {
        "Type": "Bid",
        "Price": 67674.0,
        "Quantity": 20,
        "Total": 1353480.0,
        "ProductType": "Options",
        "Time": "2020-08-04T20:07:46"
      },
      {
        "Type": "Bid",
        "Price": 4200.0,
        "Quantity": 164332,
        "Total": 690194400.0,
        "ProductType": "Equities",
        "Time": "2023-05-24T19:05:24.1910854+02:00"
      },
      {
        "Type": "Bid",
        "Price": 3940.0,
        "Quantity": 504,
        "Total": 1985760.0,
        "ProductType": "Options",
        "Time": "2019-03-08T04:48:46"
      },
      {
        "Type": "Bid",
        "Price": 3443.0,
        "Quantity": 33,
        "Total": 113619.0,
        "ProductType": "Futures",
        "Time": "2021-08-07T23:06:29"
      },
      {
        "Type": "Bid",
        "Price": 3432.0,
        "Quantity": 179,
        "Total": 614328.0,
        "ProductType": "Options",
        "Time": "2019-02-10T19:48:40"
      },
      {
        "Type": "Bid",
        "Price": 3333.0,
        "Quantity": 2770,
        "Total": 9232410.0,
        "ProductType": "Equities",
        "Time": "2019-10-29T19:15:51"
      },
      {
        "Type": "Bid",
        "Price": 3332.0,
        "Quantity": 3,
        "Total": 9996.0,
        "ProductType": "Options",
        "Time": "2021-05-31T02:06:49"
      },
      {
        "Type": "Bid",
        "Price": 3100.0,
        "Quantity": 1221,
        "Total": 3785100.0,
        "ProductType": "Equities",
        "Time": "2018-01-07T19:01:06"
      },
      {
        "Type": "Bid",
        "Price": 2900.0,
        "Quantity": 3,
        "Total": 8700.0,
        "ProductType": "Futures",
        "Time": "2019-08-14T16:05:44"
      },
      {
        "Type": "Bid",
        "Price": 1843.0,
        "Quantity": 35,
        "Total": 64505.0,
        "ProductType": "Options",
        "Time": "2021-04-11T07:58:21"
      },
      {
        "Type": "Bid",
        "Price": 666.0,
        "Quantity": 5090,
        "Total": 3389940.0,
        "ProductType": "Futures",
        "Time": "2023-05-23T20:00:53.3943771+02:00"
      },
      {
        "Type": "Bid",
        "Price": 444.0,
        "Quantity": 3333,
        "Total": 1479852.0,
        "ProductType": "Options",
        "Time": "2023-05-23T21:01:13.9494962+02:00"
      }
    ],
    "Asks": [
      {
        "Type": "Ask",
        "Price": 121212.0,
        "Quantity": 27,
        "Total": 3272724.0,
        "ProductType": "Options",
        "Time": "2023-05-24T19:10:11.7587233+02:00"
      },
      {
        "Type": "Ask",
        "Price": 44444.0,
        "Quantity": 27215,
        "Total": 1209543460.0,
        "ProductType": "Equities",
        "Time": "2023-05-23T20:40:27.2052404+02:00"
      },
      {
        "Type": "Ask",
        "Price": 43415.0,
        "Quantity": 1,
        "Total": 43415.0,
        "ProductType": "Options",
        "Time": "2023-05-26T11:08:24.058712+02:00"
      },
      {
        "Type": "Ask",
        "Price": 43343.0,
        "Quantity": 4444,
        "Total": 0.0,
        "ProductType": "Futures",
        "Time": "2023-05-27T10:34:23.4214862+02:00"
      },
      {
        "Type": "Ask",
        "Price": 11111.0,
        "Quantity": 5632,
        "Total": 0.0,
        "ProductType": "Equities",
        "Time": "2023-05-27T10:34:35.5602963+02:00"
      },
      {
        "Type": "Ask",
        "Price": 4345.0,
        "Quantity": 2024,
        "Total": 8794280.0,
        "ProductType": "Bonds",
        "Time": "2019-05-13T10:29:17"
      },
      {
        "Type": "Ask",
        "Price": 3947.0,
        "Quantity": 7019,
        "Total": 33498189.0,
        "ProductType": "Equities",
        "Time": "2020-10-02T12:19:46"
      },
      {
        "Type": "Ask",
        "Price": 3333.0,
        "Quantity": 1659,
        "Total": 5529447.0,
        "ProductType": "Options",
        "Time": "2023-05-23T20:42:16.8176385+02:00"
      },
      {
        "Type": "Ask",
        "Price": 2321.0,
        "Quantity": 99,
        "Total": 229779.0,
        "ProductType": "Options",
        "Time": "2019-09-27T08:07:07"
      },
      {
        "Type": "Ask",
        "Price": 1212.0,
        "Quantity": 5,
        "Total": 6060.0,
        "ProductType": "Options",
        "Time": "2019-02-05T21:57:43"
      },
      {
        "Type": "Ask",
        "Price": 1112.0,
        "Quantity": 21,
        "Total": 23352.0,
        "ProductType": "Options",
        "Time": "2018-05-11T17:45:42"
      },
      {
        "Type": "Ask",
        "Price": 333.0,
        "Quantity": 6635,
        "Total": 2209455.0,
        "ProductType": "Options",
        "Time": "2018-07-14T18:54:01"
      },
      {
        "Type": "Ask",
        "Price": 32.0,
        "Quantity": 162,
        "Total": 5184.0,
        "ProductType": "Options",
        "Time": "2021-03-20T20:19:16"
      }
    ]
  },
  {
    "Ticker": {
      "Symbol": "AAPL"
    },
    "Bids": [
      {
        "Type": "Bid",
        "Price": 62642.0,
        "Quantity": 2346,
        "Total": 0.0,
        "ProductType": "Options",
        "Time": "2023-05-27T10:35:28.4194613+02:00"
      },
      {
        "Type": "Bid",
        "Price": 12345.0,
        "Quantity": 205,
        "Total": 2530725.0,
        "ProductType": "Futures",
        "Time": "2023-05-26T17:52:10.7936241+02:00"
      },
      {
        "Type": "Bid",
        "Price": 11242.0,
        "Quantity": 2346,
        "Total": 0.0,
        "ProductType": "Options",
        "Time": "2023-05-27T10:35:22.6858824+02:00"
      },
      {
        "Type": "Bid",
        "Price": 7864.0,
        "Quantity": 109,
        "Total": 857176.0,
        "ProductType": "Futures",
        "Time": "2023-05-26T17:52:24.0108049+02:00"
      },
      {
        "Type": "Bid",
        "Price": 6242.0,
        "Quantity": 2346,
        "Total": 0.0,
        "ProductType": "Options",
        "Time": "2023-05-27T10:35:25.7747084+02:00"
      },
      {
        "Type": "Bid",
        "Price": 5866.0,
        "Quantity": 73,
        "Total": 428218.0,
        "ProductType": "Equities",
        "Time": "2020-11-10T03:19:45"
      },
      {
        "Type": "Bid",
        "Price": 5544.0,
        "Quantity": 9836,
        "Total": 54530784.0,
        "ProductType": "Bonds",
        "Time": "2019-10-17T19:21:42"
      },
      {
        "Type": "Bid",
        "Price": 5269.0,
        "Quantity": 1456,
        "Total": 7671664.0,
        "ProductType": "Futures",
        "Time": "2020-03-30T18:04:21"
      },
      {
        "Type": "Bid",
        "Price": 4977.0,
        "Quantity": 333,
        "Total": 1657341.0,
        "ProductType": "Options",
        "Time": "2023-05-26T17:52:47.1727655+02:00"
      },
      {
        "Type": "Bid",
        "Price": 4723.0,
        "Quantity": 5550,
        "Total": 26212650.0,
        "ProductType": "Equities",
        "Time": "2019-07-15T21:59:31"
      },
      {
        "Type": "Bid",
        "Price": 4077.0,
        "Quantity": 885,
        "Total": 3608145.0,
        "ProductType": "Bonds",
        "Time": "2021-11-29T11:16:49"
      },
      {
        "Type": "Bid",
        "Price": 3843.0,
        "Quantity": 359,
        "Total": 1379637.0,
        "ProductType": "Bonds",
        "Time": "2020-11-27T05:13:30"
      },
      {
        "Type": "Bid",
        "Price": 1122.0,
        "Quantity": 1003,
        "Total": 1125366.0,
        "ProductType": "Futures",
        "Time": "2018-03-20T14:03:45"
      }
    ],
    "Asks": [
      {
        "Type": "Ask",
        "Price": 63305.1,
        "Quantity": 279,
        "Total": 17662122.9,
        "ProductType": "Bonds",
        "Time": "2023-05-24T18:45:49.8246773+02:00"
      },
      {
        "Type": "Ask",
        "Price": 63305.0,
        "Quantity": 2444,
        "Total": 154717420.0,
        "ProductType": "Bonds",
        "Time": "2018-09-14T01:12:16"
      },
      {
        "Type": "Ask",
        "Price": 43321.0,
        "Quantity": 2323,
        "Total": 100634683.0,
        "ProductType": "Options",
        "Time": "2019-01-04T09:06:26"
      },
      {
        "Type": "Ask",
        "Price": 6632.0,
        "Quantity": 347,
        "Total": 2301304.0,
        "ProductType": "Equities",
        "Time": "2021-11-23T22:29:36"
      },
      {
        "Type": "Ask",
        "Price": 6305.0,
        "Quantity": 2122,
        "Total": 13379210.0,
        "ProductType": "Bonds",
        "Time": "2018-02-21T18:47:48"
      },
      {
        "Type": "Ask",
        "Price": 5998.0,
        "Quantity": 1470,
        "Total": 8817060.0,
        "ProductType": "Options",
        "Time": "2021-09-25T18:04:18"
      },
      {
        "Type": "Ask",
        "Price": 5672.0,
        "Quantity": 11,
        "Total": 62392.0,
        "ProductType": "Futures",
        "Time": "2021-02-11T06:02:01"
      },
      {
        "Type": "Ask",
        "Price": 5379.0,
        "Quantity": 7027,
        "Total": 37798233.0,
        "ProductType": "Options",
        "Time": "2019-04-01T20:50:41"
      },
      {
        "Type": "Ask",
        "Price": 5075.0,
        "Quantity": 590,
        "Total": 2994250.0,
        "ProductType": "Equities",
        "Time": "2020-08-03T01:15:04"
      },
      {
        "Type": "Ask",
        "Price": 4752.0,
        "Quantity": 302,
        "Total": 2238192.0,
        "ProductType": "Bonds",
        "Time": "2021-07-22T15:37:46"
      },
      {
        "Type": "Ask",
        "Price": 4453.0,
        "Quantity": 6818,
        "Total": 30360554.0,
        "ProductType": "Bonds",
        "Time": "2019-11-12T20:57:26"
      },
      {
        "Type": "Ask",
        "Price": 4322.0,
        "Quantity": 43,
        "Total": 185846.0,
        "ProductType": "Options",
        "Time": "2018-03-14T13:34:43"
      },
      {
        "Type": "Ask",
        "Price": 4176.0,
        "Quantity": 343,
        "Total": 1432368.0,
        "ProductType": "Futures",
        "Time": "2021-08-15T18:20:44"
      }
    ]
  },
  {
    "Ticker": {
      "Symbol": "AMZN"
    },
    "Bids": [
      {
        "Type": "Bid",
        "Price": 21411.0,
        "Quantity": 213,
        "Total": 0.0,
        "ProductType": "Options",
        "Time": "2023-05-27T10:34:52.481239+02:00"
      },
      {
        "Type": "Bid",
        "Price": 12333.0,
        "Quantity": 8,
        "Total": 98664.0,
        "ProductType": "Options",
        "Time": "2020-08-23T00:37:25"
      },
      {
        "Type": "Bid",
        "Price": 12222.0,
        "Quantity": 213,
        "Total": 0.0,
        "ProductType": "Options",
        "Time": "2023-05-27T10:34:55.5645531+02:00"
      },
      {
        "Type": "Bid",
        "Price": 7866.0,
        "Quantity": 213,
        "Total": 0.0,
        "ProductType": "Options",
        "Time": "2023-05-27T10:35:00.7250907+02:00"
      },
      {
        "Type": "Bid",
        "Price": 6723.0,
        "Quantity": 159,
        "Total": 1068957.0,
        "ProductType": "Futures",
        "Time": "2020-05-02T14:45:45"
      },
      {
        "Type": "Bid",
        "Price": 5719.0,
        "Quantity": 112,
        "Total": 640528.0,
        "ProductType": "Bonds",
        "Time": "2021-07-31T08:12:24"
      },
      {
        "Type": "Bid",
        "Price": 5432.0,
        "Quantity": 856,
        "Total": 4649792.0,
        "ProductType": "Equities",
        "Time": "2018-12-09T13:02:55"
      },
      {
        "Type": "Bid",
        "Price": 4843.0,
        "Quantity": 1205,
        "Total": 5835815.0,
        "ProductType": "Equities",
        "Time": "2021-02-02T16:49:56"
      },
      {
        "Type": "Bid",
        "Price": 4206.0,
        "Quantity": 1708,
        "Total": 7183848.0,
        "ProductType": "Bonds",
        "Time": "2018-12-13T16:13:43"
      },
      {
        "Type": "Bid",
        "Price": 3932.0,
        "Quantity": 1452,
        "Total": 21551292.0,
        "ProductType": "Options",
        "Time": "2018-01-08T09:46:01"
      },
      {
        "Type": "Bid",
        "Price": 3434.0,
        "Quantity": 1,
        "Total": 3434.0,
        "ProductType": "Options",
        "Time": "2018-07-23T10:53:49"
      },
      {
        "Type": "Bid",
        "Price": 1233.0,
        "Quantity": 33,
        "Total": 40689.0,
        "ProductType": "Options",
        "Time": "2019-12-18T01:32:10"
      }
    ],
    "Asks": [
      {
        "Type": "Ask",
        "Price": 78661.0,
        "Quantity": 213,
        "Total": 0.0,
        "ProductType": "Equities",
        "Time": "2023-05-27T10:35:11.5964945+02:00"
      },
      {
        "Type": "Ask",
        "Price": 7866.0,
        "Quantity": 213,
        "Total": 0.0,
        "ProductType": "Equities",
        "Time": "2023-05-27T10:35:07.7493746+02:00"
      },
      {
        "Type": "Ask",
        "Price": 6666.0,
        "Quantity": 2079,
        "Total": 13858614.0,
        "ProductType": "Options",
        "Time": "2018-02-09T18:54:04"
      },
      {
        "Type": "Ask",
        "Price": 6565.0,
        "Quantity": 563,
        "Total": 3696095.0,
        "ProductType": "Options",
        "Time": "2021-02-13T17:31:22"
      },
      {
        "Type": "Ask",
        "Price": 6031.0,
        "Quantity": 1440,
        "Total": 8684640.0,
        "ProductType": "Futures",
        "Time": "2020-09-30T16:30:53"
      },
      {
        "Type": "Ask",
        "Price": 5735.0,
        "Quantity": 4527,
        "Total": 25962345.0,
        "ProductType": "Equities",
        "Time": "2018-02-19T03:02:52"
      },
      {
        "Type": "Ask",
        "Price": 5477.0,
        "Quantity": 153,
        "Total": 837981.0,
        "ProductType": "Bonds",
        "Time": "2019-12-13T14:57:47"
      },
      {
        "Type": "Ask",
        "Price": 5150.0,
        "Quantity": 889,
        "Total": 4578350.0,
        "ProductType": "Options",
        "Time": "2021-09-21T06:43:42"
      },
      {
        "Type": "Ask",
        "Price": 4883.0,
        "Quantity": 2157,
        "Total": 10532631.0,
        "ProductType": "Equities",
        "Time": "2020-07-09T20:17:27"
      },
      {
        "Type": "Ask",
        "Price": 4543.0,
        "Quantity": 29,
        "Total": 131747.0,
        "ProductType": "Options",
        "Time": "2023-05-26T15:24:07.901565+02:00"
      },
      {
        "Type": "Ask",
        "Price": 3976.0,
        "Quantity": 4452,
        "Total": 17701152.0,
        "ProductType": "Bonds",
        "Time": "2018-07-04T09:05:12"
      },
      {
        "Type": "Ask",
        "Price": 3434.0,
        "Quantity": 1,
        "Total": 3434.0,
        "ProductType": "Options",
        "Time": "2019-06-08T03:31:47"
      },
      {
        "Type": "Ask",
        "Price": 332.0,
        "Quantity": 332,
        "Total": 110224.0,
        "ProductType": "Options",
        "Time": "2020-08-10T10:16:24"
      }
    ]
  },
  {
    "Ticker": {
      "Symbol": "MSFT"
    },
    "Bids": [
      {
        "Type": "Bid",
        "Price": 565656.0,
        "Quantity": 14,
        "Total": 7919184.0,
        "ProductType": "Options",
        "Time": "2019-12-16T01:02:16"
      },
      {
        "Type": "Bid",
        "Price": 23453.0,
        "Quantity": 179,
        "Total": 4198087.0,
        "ProductType": "Futures",
        "Time": "2023-05-26T16:20:28.9877219+02:00"
      },
      {
        "Type": "Bid",
        "Price": 6675.0,
        "Quantity": 433,
        "Total": 0.0,
        "ProductType": "Bonds",
        "Time": "2023-05-27T10:35:59.0756184+02:00"
      },
      {
        "Type": "Bid",
        "Price": 6442.0,
        "Quantity": 3211,
        "Total": 20685262.0,
        "ProductType": "Bonds",
        "Time": "2023-05-26T16:20:59.6638631+02:00"
      },
      {
        "Type": "Bid",
        "Price": 6119.0,
        "Quantity": 9132,
        "Total": 55878708.0,
        "ProductType": "Options",
        "Time": "2021-03-25T07:40:39"
      },
      {
        "Type": "Bid",
        "Price": 5812.0,
        "Quantity": 458,
        "Total": 2661896.0,
        "ProductType": "Equities",
        "Time": "2021-03-13T19:45:53"
      },
      {
        "Type": "Bid",
        "Price": 5245.0,
        "Quantity": 735,
        "Total": 3855075.0,
        "ProductType": "Bonds",
        "Time": "2020-07-31T15:57:02"
      },
      {
        "Type": "Bid",
        "Price": 4589.0,
        "Quantity": 3449,
        "Total": 15827461.0,
        "ProductType": "Equities",
        "Time": "2021-12-01T13:52:42"
      },
      {
        "Type": "Bid",
        "Price": 3974.01,
        "Quantity": 20393,
        "Total": 81041985.93,
        "ProductType": "Equities",
        "Time": "2021-03-06T03:12:04"
      },
      {
        "Type": "Bid",
        "Price": 3974.0,
        "Quantity": 73104,
        "Total": 290515296.0,
        "ProductType": "Equities",
        "Time": "2021-05-29T18:26:35"
      },
      {
        "Type": "Bid",
        "Price": 3333.0,
        "Quantity": 43,
        "Total": 0.0,
        "ProductType": "Options",
        "Time": "2023-05-27T10:35:48.4982091+02:00"
      },
      {
        "Type": "Bid",
        "Price": 3333.0,
        "Quantity": 43,
        "Total": 0.0,
        "ProductType": "Equities",
        "Time": "2023-05-27T10:35:51.0184162+02:00"
      }
    ],
    "Asks": [
      {
        "Type": "Ask",
        "Price": 75655.0,
        "Quantity": 43,
        "Total": 0.0,
        "ProductType": "Options",
        "Time": "2023-05-27T10:35:41.3439323+02:00"
      },
      {
        "Type": "Ask",
        "Price": 6992.0,
        "Quantity": 1854,
        "Total": 12963168.0,
        "ProductType": "Bonds",
        "Time": "2020-10-03T06:18:33"
      },
      {
        "Type": "Ask",
        "Price": 6621.0,
        "Quantity": 2,
        "Total": 132420.0,
        "ProductType": "Futures",
        "Time": "2018-12-05T07:44:08"
      },
      {
        "Type": "Ask",
        "Price": 6309.0,
        "Quantity": 1212,
        "Total": 7646508.0,
        "ProductType": "Options",
        "Time": "2021-10-29T13:40:11"
      },
      {
        "Type": "Ask",
        "Price": 5986.0,
        "Quantity": 1111,
        "Total": 6650446.0,
        "ProductType": "Equities",
        "Time": "2020-09-13T21:31:01"
      },
      {
        "Type": "Ask",
        "Price": 5674.0,
        "Quantity": 2564,
        "Total": 14548136.0,
        "ProductType": "Bonds",
        "Time": "2018-11-02T23:27:27"
      },
      {
        "Type": "Ask",
        "Price": 5345.0,
        "Quantity": 66,
        "Total": 352770.0,
        "ProductType": "Equities",
        "Time": "2019-06-09T23:36:03"
      },
      {
        "Type": "Ask",
        "Price": 5011.0,
        "Quantity": 1797,
        "Total": 9004767.0,
        "ProductType": "Options",
        "Time": "2019-03-01T22:21:30"
      },
      {
        "Type": "Ask",
        "Price": 4715.0,
        "Quantity": 46,
        "Total": 216890.0,
        "ProductType": "Options",
        "Time": "2021-01-09T23:06:24"
      },
      {
        "Type": "Ask",
        "Price": 4545.0,
        "Quantity": 3333,
        "Total": 15148485.0,
        "ProductType": "Options",
        "Time": "2018-01-07T17:13:59"
      },
      {
        "Type": "Ask",
        "Price": 4378.0,
        "Quantity": 2936,
        "Total": 12853808.0,
        "ProductType": "Bonds",
        "Time": "2018-10-21T14:38:22"
      },
      {
        "Type": "Ask",
        "Price": 3333.0,
        "Quantity": 43,
        "Total": 0.0,
        "ProductType": "Options",
        "Time": "2023-05-27T10:35:44.8443487+02:00"
      }
    ]
  }
]